prettyjunit/__init__.py
prettyjunit/convert.py
prettyjunit/report_template.html
prettyjunit-0.0.4.dist-info/License.txt
prettyjunit-0.0.4.dist-info/METADATA
prettyjunit-0.0.4.dist-info/WHEEL
prettyjunit-0.0.4.dist-info/entry_points.txt
prettyjunit-0.0.4.dist-info/top_level.txt
prettyjunit-0.0.4.dist-info/RECORD
